README.rst
setup.py
django_dyn_reports.egg-info/PKG-INFO
django_dyn_reports.egg-info/SOURCES.txt
django_dyn_reports.egg-info/dependency_links.txt
django_dyn_reports.egg-info/requires.txt
django_dyn_reports.egg-info/top_level.txt
django_reports/__init__.py
django_reports/admin.py
django_reports/highcharts.py
django_reports/models.py
django_reports/reports.py
django_reports/settings.py
django_reports/tests.py
django_reports/urls.py
django_reports/utils.py
django_reports/wsgi.py
django_reports/migrations/0001_initial.py
django_reports/migrations/0002_auto_20170902_1448.py
django_reports/migrations/__init__.py